{
  "additional_properties": false,
  "type": "object",
  "properties": {
    "$ref": "common.json",
    "line_item_type": {
      "type": ["null", "string"]
    },
    "segment_class_code": {
      "type": ["null", "string"]
    },
    "targeting_method": {
      "type": ["null", "string"]
    },
    "segment_marketplace_id": {
      "type": ["null", "integer"]
    },
    "interval_start": {
      "type": ["null", "string"],
      "format": "date-time"
    },
    "interval_end": {
      "type": ["null", "string"],
      "format": "date-time"
    },
    "segment_type": {
      "type": ["null", "string"]
    },
    "segment": {
      "type": ["null", "string"]
    },
    "segment_source": {
      "type": ["null", "string"]
    }
  }
}